weni_datalake_sdk/__init__.py
weni_datalake_sdk/clients/__init__.py
weni_datalake_sdk/clients/client.py
weni_datalake_sdk/clients/commerce_webhook_pb2.py
weni_datalake_sdk/clients/commerce_webhook_pb2_grpc.py
weni_datalake_sdk/clients/dl_manager_client.py
weni_datalake_sdk/clients/events_pb2.py
weni_datalake_sdk/clients/events_pb2_grpc.py
weni_datalake_sdk/clients/insert.py
weni_datalake_sdk/clients/message_templates_pb2.py
weni_datalake_sdk/clients/message_templates_pb2_grpc.py
weni_datalake_sdk/clients/msgs_pb2.py
weni_datalake_sdk/clients/msgs_pb2_grpc.py
weni_datalake_sdk/clients/proto/__init__.py
weni_datalake_sdk/clients/proto/commerce_webhook.proto
weni_datalake_sdk/clients/proto/events.proto
weni_datalake_sdk/clients/proto/message_templates.proto
weni_datalake_sdk/clients/proto/msgs.proto
weni_datalake_sdk/clients/proto/traces.proto
weni_datalake_sdk/clients/redshift/__init__.py
weni_datalake_sdk/clients/redshift/events.py
weni_datalake_sdk/clients/redshift/message_templates.py
weni_datalake_sdk/clients/redshift/redshift_client.py
weni_datalake_sdk/clients/redshift/traces.py
weni_datalake_sdk/clients/traces_pb2.py
weni_datalake_sdk/clients/traces_pb2_grpc.py
weni_datalake_sdk/paths/__init__.py
weni_datalake_sdk/paths/base_path.py
weni_datalake_sdk/paths/commerce_webhook.py
weni_datalake_sdk/paths/events_path.py
weni_datalake_sdk/paths/message_template_path.py
weni_datalake_sdk/paths/message_template_status_path.py
weni_datalake_sdk/paths/msg_path.py
weni_datalake_sdk/paths/trace_path.py
weni_datalake_sdk/paths/validator.py
weni_datalake_sdk/tests/__init__.py
weni_datalake_sdk/tests/test_clients.py
weni_datalake_sdk/tests/test_commerce_webhook.py
weni_datalake_sdk/tests/test_events.py
weni_datalake_sdk/tests/test_message_templates.py
weni_datalake_sdk/tests/test_paths.py
weni_datalake_sdk/tests/test_redshift_client.py
weni_datalake_sdk/tests/test_validator.py
weni_datalake_sdk/utils/__init__.py
weni_datalake_sdk/utils/exceptions.py
weni_datalake_sdk-0.6.0.dist-info/LICENSE
weni_datalake_sdk-0.6.0.dist-info/METADATA
weni_datalake_sdk-0.6.0.dist-info/WHEEL
weni_datalake_sdk-0.6.0.dist-info/RECORD
